spookyotp/__init__.py
spookyotp/byte_util.py
spookyotp/otp.py
SpookyOTP-1.1.4.dist-info/LICENSE
SpookyOTP-1.1.4.dist-info/METADATA
SpookyOTP-1.1.4.dist-info/WHEEL
SpookyOTP-1.1.4.dist-info/top_level.txt
SpookyOTP-1.1.4.dist-info/zip-safe
SpookyOTP-1.1.4.dist-info/RECORD
